pytest_playwright_axe/__init__.py
pytest_playwright_axe/axe.py
pytest_playwright_axe/resources/axe.js
pytest_playwright_axe/resources/axe.min.js
pytest_playwright_axe/resources/default.css
pytest_playwright_axe-4.11.0.dist-info/licenses/LICENCE.md
pytest_playwright_axe-4.11.0.dist-info/METADATA
pytest_playwright_axe-4.11.0.dist-info/WHEEL
pytest_playwright_axe-4.11.0.dist-info/top_level.txt
pytest_playwright_axe-4.11.0.dist-info/RECORD
