Metadata-Version: 2.4
Name: pytest-playwright-axe
Version: 4.11.0
Summary: An axe-core integration for accessibility testing using Playwright Python.
Author-email: Dave Harding <dave@punkamania.org>
License-Expression: MIT
Project-URL: Homepage, https://github.com/davethepunkyone/pytest-playwright-axe
Project-URL: Repository, https://github.com/davethepunkyone/pytest-playwright-axe
Project-URL: Issues, https://github.com/davethepunkyone/pytest-playwright-axe/issues
Keywords: accessibility,playwright,axe,axe-core,pytest,wcag,testing
Classifier: Development Status :: 5 - Production/Stable
Classifier: Topic :: Software Development :: Testing
Classifier: Framework :: Pytest
Classifier: Operating System :: OS Independent
Classifier: Programming Language :: Python :: 3
Classifier: Programming Language :: Python :: 3.12
Classifier: Programming Language :: Python :: 3.13
Requires-Python: >=3.12
License-File: LICENCE.md
Requires-Dist: pytest-playwright>=0.5.1
Dynamic: license-file
